{
  "mode": "high-risk",
  "selected_pages": [
    1,
    5,
    6,
    7,
    8,
    9,
    11,
    12
  ],
  "required_block_ids": [
    "p1:0",
    "p1:1",
    "p1:2",
    "p1:3",
    "p1:4",
    "p1:5",
    "p1:6",
    "p1:7",
    "p1:8",
    "p1:9",
    "p1:10",
    "p1:11",
    "p1:12",
    "p1:13",
    "p1:14",
    "p1:15",
    "p1:16",
    "p1:17",
    "p1:18",
    "p1:19",
    "p1:20",
    "p1:21",
    "p1:22",
    "p1:23",
    "p5:2",
    "p5:6",
    "p6:3",
    "p6:7",
    "p6:8",
    "p6:11",
    "p6:13",
    "p7:5",
    "p7:7",
    "p7:8",
    "p7:11",
    "p7:12",
    "p8:3",
    "p8:5",
    "p8:6",
    "p8:8",
    "p8:10",
    "p8:13",
    "p8:14",
    "p8:16",
    "p9:5",
    "p9:7",
    "p9:8",
    "p9:10",
    "p9:12",
    "p11:0",
    "p11:2",
    "p11:4",
    "p11:5",
    "p11:6",
    "p11:7",
    "p11:8",
    "p12:5",
    "p12:6",
    "p12:10",
    "p12:11",
    "p12:12",
    "p12:13",
    "p12:14",
    "p12:15",
    "p12:16",
    "p12:17",
    "p12:18",
    "p12:19",
    "p12:20"
  ],
  "required_blocks": [
    {
      "block_id": "p1:0",
      "page": 1,
      "required_reason": [
        "frontmatter"
      ],
      "minimum_fields": [
        "block_id",
        "page",
        "review_status",
        "truth_role",
        "truth_zone",
        "truth_reference_membership"
      ]
    },
    {
      "block_id": "p1:1",
      "page": 1,
      "required_reason": [
        "frontmatter"
      ],
      "minimum_fields": [
        "block_id",
        "page",
        "review_status",
        "truth_role",
        "truth_zone",
        "truth_reference_membership"
      ]
    },
    {
      "block_id": "p1:2",
      "page": 1,
      "required_reason": [
        "frontmatter"
      ],
      "minimum_fields": [
        "block_id",
        "page",
        "review_status",
        "truth_role",
        "truth_zone",
        "truth_reference_membership"
      ]
    },
    {
      "block_id": "p1:3",
      "page": 1,
      "required_reason": [
        "frontmatter"
      ],
      "minimum_fields": [
        "block_id",
        "page",
        "review_status",
        "truth_role",
        "truth_zone",
        "truth_reference_membership"
      ]
    },
    {
      "block_id": "p1:4",
      "page": 1,
      "required_reason": [
        "frontmatter"
      ],
      "minimum_fields": [
        "block_id",
        "page",
        "review_status",
        "truth_role",
        "truth_zone",
        "truth_reference_membership"
      ]
    },
    {
      "block_id": "p1:5",
      "page": 1,
      "required_reason": [
        "frontmatter"
      ],
      "minimum_fields": [
        "block_id",
        "page",
        "review_status",
        "truth_role",
        "truth_zone",
        "truth_reference_membership"
      ]
    },
    {
      "block_id": "p1:6",
      "page": 1,
      "required_reason": [
        "frontmatter"
      ],
      "minimum_fields": [
        "block_id",
        "page",
        "review_status",
        "truth_role",
        "truth_zone",
        "truth_reference_membership"
      ]
    },
    {
      "block_id": "p1:7",
      "page": 1,
      "required_reason": [
        "frontmatter"
      ],
      "minimum_fields": [
        "block_id",
        "page",
        "review_status",
        "truth_role",
        "truth_zone",
        "truth_reference_membership"
      ]
    },
    {
      "block_id": "p1:8",
      "page": 1,
      "required_reason": [
        "frontmatter"
      ],
      "minimum_fields": [
        "block_id",
        "page",
        "review_status",
        "truth_role",
        "truth_zone",
        "truth_reference_membership"
      ]
    },
    {
      "block_id": "p1:9",
      "page": 1,
      "required_reason": [
        "frontmatter",
        "object_ownership"
      ],
      "minimum_fields": [
        "block_id",
        "page",
        "review_status",
        "truth_role",
        "truth_zone",
        "truth_reference_membership"
      ]
    },
    {
      "block_id": "p1:10",
      "page": 1,
      "required_reason": [
        "frontmatter"
      ],
      "minimum_fields": [
        "block_id",
        "page",
        "review_status",
        "truth_role",
        "truth_zone",
        "truth_reference_membership"
      ]
    },
    {
      "block_id": "p1:11",
      "page": 1,
      "required_reason": [
        "frontmatter",
        "object_ownership"
      ],
      "minimum_fields": [
        "block_id",
        "page",
        "review_status",
        "truth_role",
        "truth_zone",
        "truth_reference_membership"
      ]
    },
    {
      "block_id": "p1:12",
      "page": 1,
      "required_reason": [
        "frontmatter"
      ],
      "minimum_fields": [
        "block_id",
        "page",
        "review_status",
        "truth_role",
        "truth_zone",
        "truth_reference_membership"
      ]
    },
    {
      "block_id": "p1:13",
      "page": 1,
      "required_reason": [
        "frontmatter"
      ],
      "minimum_fields": [
        "block_id",
        "page",
        "review_status",
        "truth_role",
        "truth_zone",
        "truth_reference_membership"
      ]
    },
    {
      "block_id": "p1:14",
      "page": 1,
      "required_reason": [
        "frontmatter"
      ],
      "minimum_fields": [
        "block_id",
        "page",
        "review_status",
        "truth_role",
        "truth_zone",
        "truth_reference_membership"
      ]
    },
    {
      "block_id": "p1:15",
      "page": 1,
      "required_reason": [
        "frontmatter"
      ],
      "minimum_fields": [
        "block_id",
        "page",
        "review_status",
        "truth_role",
        "truth_zone",
        "truth_reference_membership"
      ]
    },
    {
      "block_id": "p1:16",
      "page": 1,
      "required_reason": [
        "frontmatter"
      ],
      "minimum_fields": [
        "block_id",
        "page",
        "review_status",
        "truth_role",
        "truth_zone",
        "truth_reference_membership"
      ]
    },
    {
      "block_id": "p1:17",
      "page": 1,
      "required_reason": [
        "frontmatter"
      ],
      "minimum_fields": [
        "block_id",
        "page",
        "review_status",
        "truth_role",
        "truth_zone",
        "truth_reference_membership"
      ]
    },
    {
      "block_id": "p1:18",
      "page": 1,
      "required_reason": [
        "frontmatter"
      ],
      "minimum_fields": [
        "block_id",
        "page",
        "review_status",
        "truth_role",
        "truth_zone",
        "truth_reference_membership"
      ]
    },
    {
      "block_id": "p1:19",
      "page": 1,
      "required_reason": [
        "frontmatter"
      ],
      "minimum_fields": [
        "block_id",
        "page",
        "review_status",
        "truth_role",
        "truth_zone",
        "truth_reference_membership"
      ]
    },
    {
      "block_id": "p1:20",
      "page": 1,
      "required_reason": [
        "frontmatter"
      ],
      "minimum_fields": [
        "block_id",
        "page",
        "review_status",
        "truth_role",
        "truth_zone",
        "truth_reference_membership"
      ]
    },
    {
      "block_id": "p1:21",
      "page": 1,
      "required_reason": [
        "frontmatter"
      ],
      "minimum_fields": [
        "block_id",
        "page",
        "review_status",
        "truth_role",
        "truth_zone",
        "truth_reference_membership"
      ]
    },
    {
      "block_id": "p1:22",
      "page": 1,
      "required_reason": [
        "frontmatter"
      ],
      "minimum_fields": [
        "block_id",
        "page",
        "review_status",
        "truth_role",
        "truth_zone",
        "truth_reference_membership"
      ]
    },
    {
      "block_id": "p1:23",
      "page": 1,
      "required_reason": [
        "frontmatter"
      ],
      "minimum_fields": [
        "block_id",
        "page",
        "review_status",
        "truth_role",
        "truth_zone",
        "truth_reference_membership"
      ]
    },
    {
      "block_id": "p5:2",
      "page": 5,
      "required_reason": [
        "object_ownership"
      ],
      "minimum_fields": [
        "block_id",
        "page",
        "review_status",
        "truth_role",
        "truth_zone",
        "truth_reference_membership"
      ]
    },
    {
      "block_id": "p5:6",
      "page": 5,
      "required_reason": [
        "object_ownership"
      ],
      "minimum_fields": [
        "block_id",
        "page",
        "review_status",
        "truth_role",
        "truth_zone",
        "truth_reference_membership"
      ]
    },
    {
      "block_id": "p6:3",
      "page": 6,
      "required_reason": [
        "object_ownership"
      ],
      "minimum_fields": [
        "block_id",
        "page",
        "review_status",
        "truth_role",
        "truth_zone",
        "truth_reference_membership"
      ]
    },
    {
      "block_id": "p6:7",
      "page": 6,
      "required_reason": [
        "object_ownership"
      ],
      "minimum_fields": [
        "block_id",
        "page",
        "review_status",
        "truth_role",
        "truth_zone",
        "truth_reference_membership"
      ]
    },
    {
      "block_id": "p6:8",
      "page": 6,
      "required_reason": [
        "object_ownership"
      ],
      "minimum_fields": [
        "block_id",
        "page",
        "review_status",
        "truth_role",
        "truth_zone",
        "truth_reference_membership"
      ]
    },
    {
      "block_id": "p6:11",
      "page": 6,
      "required_reason": [
        "object_ownership"
      ],
      "minimum_fields": [
        "block_id",
        "page",
        "review_status",
        "truth_role",
        "truth_zone",
        "truth_reference_membership"
      ]
    },
    {
      "block_id": "p6:13",
      "page": 6,
      "required_reason": [
        "object_ownership"
      ],
      "minimum_fields": [
        "block_id",
        "page",
        "review_status",
        "truth_role",
        "truth_zone",
        "truth_reference_membership"
      ]
    },
    {
      "block_id": "p7:5",
      "page": 7,
      "required_reason": [
        "object_ownership"
      ],
      "minimum_fields": [
        "block_id",
        "page",
        "review_status",
        "truth_role",
        "truth_zone",
        "truth_reference_membership"
      ]
    },
    {
      "block_id": "p7:7",
      "page": 7,
      "required_reason": [
        "object_ownership"
      ],
      "minimum_fields": [
        "block_id",
        "page",
        "review_status",
        "truth_role",
        "truth_zone",
        "truth_reference_membership"
      ]
    },
    {
      "block_id": "p7:8",
      "page": 7,
      "required_reason": [
        "object_ownership"
      ],
      "minimum_fields": [
        "block_id",
        "page",
        "review_status",
        "truth_role",
        "truth_zone",
        "truth_reference_membership"
      ]
    },
    {
      "block_id": "p7:11",
      "page": 7,
      "required_reason": [
        "object_ownership"
      ],
      "minimum_fields": [
        "block_id",
        "page",
        "review_status",
        "truth_role",
        "truth_zone",
        "truth_reference_membership"
      ]
    },
    {
      "block_id": "p7:12",
      "page": 7,
      "required_reason": [
        "object_ownership"
      ],
      "minimum_fields": [
        "block_id",
        "page",
        "review_status",
        "truth_role",
        "truth_zone",
        "truth_reference_membership"
      ]
    },
    {
      "block_id": "p8:3",
      "page": 8,
      "required_reason": [
        "object_ownership"
      ],
      "minimum_fields": [
        "block_id",
        "page",
        "review_status",
        "truth_role",
        "truth_zone",
        "truth_reference_membership"
      ]
    },
    {
      "block_id": "p8:5",
      "page": 8,
      "required_reason": [
        "object_ownership"
      ],
      "minimum_fields": [
        "block_id",
        "page",
        "review_status",
        "truth_role",
        "truth_zone",
        "truth_reference_membership"
      ]
    },
    {
      "block_id": "p8:6",
      "page": 8,
      "required_reason": [
        "object_ownership"
      ],
      "minimum_fields": [
        "block_id",
        "page",
        "review_status",
        "truth_role",
        "truth_zone",
        "truth_reference_membership"
      ]
    },
    {
      "block_id": "p8:8",
      "page": 8,
      "required_reason": [
        "object_ownership"
      ],
      "minimum_fields": [
        "block_id",
        "page",
        "review_status",
        "truth_role",
        "truth_zone",
        "truth_reference_membership"
      ]
    },
    {
      "block_id": "p8:10",
      "page": 8,
      "required_reason": [
        "object_ownership"
      ],
      "minimum_fields": [
        "block_id",
        "page",
        "review_status",
        "truth_role",
        "truth_zone",
        "truth_reference_membership"
      ]
    },
    {
      "block_id": "p8:13",
      "page": 8,
      "required_reason": [
        "object_ownership"
      ],
      "minimum_fields": [
        "block_id",
        "page",
        "review_status",
        "truth_role",
        "truth_zone",
        "truth_reference_membership"
      ]
    },
    {
      "block_id": "p8:14",
      "page": 8,
      "required_reason": [
        "object_ownership"
      ],
      "minimum_fields": [
        "block_id",
        "page",
        "review_status",
        "truth_role",
        "truth_zone",
        "truth_reference_membership"
      ]
    },
    {
      "block_id": "p8:16",
      "page": 8,
      "required_reason": [
        "object_ownership"
      ],
      "minimum_fields": [
        "block_id",
        "page",
        "review_status",
        "truth_role",
        "truth_zone",
        "truth_reference_membership"
      ]
    },
    {
      "block_id": "p9:5",
      "page": 9,
      "required_reason": [
        "object_ownership"
      ],
      "minimum_fields": [
        "block_id",
        "page",
        "review_status",
        "truth_role",
        "truth_zone",
        "truth_reference_membership"
      ]
    },
    {
      "block_id": "p9:7",
      "page": 9,
      "required_reason": [
        "object_ownership"
      ],
      "minimum_fields": [
        "block_id",
        "page",
        "review_status",
        "truth_role",
        "truth_zone",
        "truth_reference_membership"
      ]
    },
    {
      "block_id": "p9:8",
      "page": 9,
      "required_reason": [
        "object_ownership"
      ],
      "minimum_fields": [
        "block_id",
        "page",
        "review_status",
        "truth_role",
        "truth_zone",
        "truth_reference_membership"
      ]
    },
    {
      "block_id": "p9:10",
      "page": 9,
      "required_reason": [
        "object_ownership"
      ],
      "minimum_fields": [
        "block_id",
        "page",
        "review_status",
        "truth_role",
        "truth_zone",
        "truth_reference_membership"
      ]
    },
    {
      "block_id": "p9:12",
      "page": 9,
      "required_reason": [
        "object_ownership"
      ],
      "minimum_fields": [
        "block_id",
        "page",
        "review_status",
        "truth_role",
        "truth_zone",
        "truth_reference_membership"
      ]
    },
    {
      "block_id": "p11:0",
      "page": 11,
      "required_reason": [
        "backmatter"
      ],
      "minimum_fields": [
        "block_id",
        "page",
        "review_status",
        "truth_role",
        "truth_zone",
        "truth_reference_membership"
      ]
    },
    {
      "block_id": "p11:2",
      "page": 11,
      "required_reason": [
        "backmatter"
      ],
      "minimum_fields": [
        "block_id",
        "page",
        "review_status",
        "truth_role",
        "truth_zone",
        "truth_reference_membership"
      ]
    },
    {
      "block_id": "p11:4",
      "page": 11,
      "required_reason": [
        "backmatter"
      ],
      "minimum_fields": [
        "block_id",
        "page",
        "review_status",
        "truth_role",
        "truth_zone",
        "truth_reference_membership"
      ]
    },
    {
      "block_id": "p11:5",
      "page": 11,
      "required_reason": [
        "backmatter"
      ],
      "minimum_fields": [
        "block_id",
        "page",
        "review_status",
        "truth_role",
        "truth_zone",
        "truth_reference_membership"
      ]
    },
    {
      "block_id": "p11:6",
      "page": 11,
      "required_reason": [
        "backmatter"
      ],
      "minimum_fields": [
        "block_id",
        "page",
        "review_status",
        "truth_role",
        "truth_zone",
        "truth_reference_membership"
      ]
    },
    {
      "block_id": "p11:7",
      "page": 11,
      "required_reason": [
        "backmatter"
      ],
      "minimum_fields": [
        "block_id",
        "page",
        "review_status",
        "truth_role",
        "truth_zone",
        "truth_reference_membership"
      ]
    },
    {
      "block_id": "p11:8",
      "page": 11,
      "required_reason": [
        "backmatter"
      ],
      "minimum_fields": [
        "block_id",
        "page",
        "review_status",
        "truth_role",
        "truth_zone",
        "truth_reference_membership"
      ]
    },
    {
      "block_id": "p12:5",
      "page": 12,
      "required_reason": [
        "same_page_boundary"
      ],
      "minimum_fields": [
        "block_id",
        "page",
        "review_status",
        "truth_role",
        "truth_zone",
        "truth_reference_membership"
      ]
    },
    {
      "block_id": "p12:6",
      "page": 12,
      "required_reason": [
        "same_page_boundary"
      ],
      "minimum_fields": [
        "block_id",
        "page",
        "review_status",
        "truth_role",
        "truth_zone",
        "truth_reference_membership"
      ]
    },
    {
      "block_id": "p12:10",
      "page": 12,
      "required_reason": [
        "frontmatter"
      ],
      "minimum_fields": [
        "block_id",
        "page",
        "review_status",
        "truth_role",
        "truth_zone",
        "truth_reference_membership"
      ]
    },
    {
      "block_id": "p12:11",
      "page": 12,
      "required_reason": [
        "reference_span"
      ],
      "minimum_fields": [
        "block_id",
        "page",
        "review_status",
        "truth_role",
        "truth_zone",
        "truth_reference_membership"
      ]
    },
    {
      "block_id": "p12:12",
      "page": 12,
      "required_reason": [
        "reference_span"
      ],
      "minimum_fields": [
        "block_id",
        "page",
        "review_status",
        "truth_role",
        "truth_zone",
        "truth_reference_membership"
      ]
    },
    {
      "block_id": "p12:13",
      "page": 12,
      "required_reason": [
        "reference_span"
      ],
      "minimum_fields": [
        "block_id",
        "page",
        "review_status",
        "truth_role",
        "truth_zone",
        "truth_reference_membership"
      ]
    },
    {
      "block_id": "p12:14",
      "page": 12,
      "required_reason": [
        "reference_span"
      ],
      "minimum_fields": [
        "block_id",
        "page",
        "review_status",
        "truth_role",
        "truth_zone",
        "truth_reference_membership"
      ]
    },
    {
      "block_id": "p12:15",
      "page": 12,
      "required_reason": [
        "reference_span"
      ],
      "minimum_fields": [
        "block_id",
        "page",
        "review_status",
        "truth_role",
        "truth_zone",
        "truth_reference_membership"
      ]
    },
    {
      "block_id": "p12:16",
      "page": 12,
      "required_reason": [
        "reference_span"
      ],
      "minimum_fields": [
        "block_id",
        "page",
        "review_status",
        "truth_role",
        "truth_zone",
        "truth_reference_membership"
      ]
    },
    {
      "block_id": "p12:17",
      "page": 12,
      "required_reason": [
        "reference_span"
      ],
      "minimum_fields": [
        "block_id",
        "page",
        "review_status",
        "truth_role",
        "truth_zone",
        "truth_reference_membership"
      ]
    },
    {
      "block_id": "p12:18",
      "page": 12,
      "required_reason": [
        "reference_span"
      ],
      "minimum_fields": [
        "block_id",
        "page",
        "review_status",
        "truth_role",
        "truth_zone",
        "truth_reference_membership"
      ]
    },
    {
      "block_id": "p12:19",
      "page": 12,
      "required_reason": [
        "reference_span"
      ],
      "minimum_fields": [
        "block_id",
        "page",
        "review_status",
        "truth_role",
        "truth_zone",
        "truth_reference_membership"
      ]
    },
    {
      "block_id": "p12:20",
      "page": 12,
      "required_reason": [
        "reference_span"
      ],
      "minimum_fields": [
        "block_id",
        "page",
        "review_status",
        "truth_role",
        "truth_zone",
        "truth_reference_membership"
      ]
    }
  ],
  "selected_page_requirements": [
    {
      "page": 1,
      "must_review_page": true,
      "required_block_count": 24
    },
    {
      "page": 5,
      "must_review_page": true,
      "required_block_count": 2
    },
    {
      "page": 6,
      "must_review_page": true,
      "required_block_count": 5
    },
    {
      "page": 7,
      "must_review_page": true,
      "required_block_count": 5
    },
    {
      "page": 8,
      "must_review_page": true,
      "required_block_count": 8
    },
    {
      "page": 9,
      "must_review_page": true,
      "required_block_count": 5
    },
    {
      "page": 11,
      "must_review_page": true,
      "required_block_count": 7
    },
    {
      "page": 12,
      "must_review_page": true,
      "required_block_count": 13
    }
  ]
}