{
  "paper_key": "2BYRLKQS",
  "mode": "high-risk",
  "status": "READY",
  "focus": [],
  "artifact_fingerprint": {
    "result_json_hash": "sha256:7268867c484bc2b5d4e9fad99d31fd113573a27115291eceb1e89ed882ef2261",
    "meta_json_hash": "sha256:b81aaa1673fe3f8d9f2af5cb3dfdc29345442bde9bba2831c50ca83d3e8442f9",
    "blocks_raw_hash": "sha256:db3bf01e4a7394b30182910c3a121bb424c79d30673c4f88a0331cbe500bf168",
    "structured_blocks_hash": "sha256:367dffc78b9559100fe4bc68a201ddb4e837fc9841c4467e5133970c6b0d01bd",
    "document_structure_hash": "sha256:8e425d134c676480c2747f69946fcbc2d6e79e8deb14b40037ae6089eba224d7",
    "figure_inventory_hash": "sha256:9b425597f600f879137ff3d2d6b333f8c751995d041f5280a1993e0f0719512c",
    "table_inventory_hash": "sha256:f6e23605db0b36875fd202e5db57e48cfad568a889a17264f80a0155d0aa9cee",
    "reader_figures_hash": "sha256:e7cc09dbbc3829ff6d7b5264917d1699ebf5027e587c5c57b13075a238eb7e7e",
    "resolved_metadata_hash": "sha256:637af4c6df06312ea992a460c1e67212122429d581f63bc4ea59d0679df33a58",
    "fulltext_hash": "sha256:341b7c796700a6f3769f32f008eec59d428daa31763bdc0fa91fafcfa4d53054",
    "block_trace_hash": "sha256:62fdae68f7e8a3b988847871a5ae245e41e43799e1ec0580019008d815efc58a",
    "annotated_pages": {
      "page_001.png": "sha256:5d51dcd307ab0df9f06f0008b8822ef7332186b494babce2b2b71bf919ce888d",
      "page_002.png": "sha256:cbe887fea4d04f55b30805343b6d5d5c1dbf3d0b23a6cc9e1e3c1693cc8de078",
      "page_003.png": "sha256:2d0025a22e92e60d0ad723698a99dfc37db88af5ae44bdd86ea8b54602061e20",
      "page_004.png": "sha256:42d2376784f6f3b782f17a4e32719af2c62ba9899ee1a1bfd8d3c35363cacc50",
      "page_005.png": "sha256:49a2d983cf4e154436bfde19c41e3505dd88f4469b15d092d2b540819d6cbd39",
      "page_006.png": "sha256:991af5cdda885f2f5a3cf66d0103289f032e0c014b6b65c23bc404cf64ad5b7c",
      "page_007.png": "sha256:b81c78d5fd91f2e28e00a1e0b5ff72a8c718f9079e70ccd488640adf0182c1b3",
      "page_008.png": "sha256:ba498baa912f824e2178bb4fba4cbfacc05f173307b782492522d907d604d2bf",
      "page_009.png": "sha256:0b1ef976ff84c108e7a65a10d3e3176136cd44c9d28b22e33403084708897cf2"
    }
  },
  "artifact_freshness": {
    "missing": [],
    "mismatches": [
      "document_structure older than blocks_structured",
      "figure_inventory older than blocks_structured",
      "table_inventory older than blocks_structured",
      "resolved_metadata older than blocks_structured"
    ],
    "annotated_pages_rendered": [
      "page_001.png",
      "page_002.png",
      "page_003.png",
      "page_004.png",
      "page_005.png",
      "page_006.png",
      "page_007.png",
      "page_008.png",
      "page_009.png"
    ]
  },
  "reviewed_pages": [
    1,
    4,
    5,
    6,
    8,
    9
  ],
  "reviewed_blocks": [
    "p1:0",
    "p1:1",
    "p1:2",
    "p1:3",
    "p1:4",
    "p1:5",
    "p1:6",
    "p1:7",
    "p1:8",
    "p1:9",
    "p1:10",
    "p1:11",
    "p1:12",
    "p1:13",
    "p1:14",
    "p1:15",
    "p1:16",
    "p1:17",
    "p1:18",
    "p1:19",
    "p1:20",
    "p1:21",
    "p4:0",
    "p4:1",
    "p4:2",
    "p4:3",
    "p4:4",
    "p4:5",
    "p4:6",
    "p4:7",
    "p4:8",
    "p4:9",
    "p5:0",
    "p5:1",
    "p5:2",
    "p5:3",
    "p5:4",
    "p5:5",
    "p6:0",
    "p6:1",
    "p6:2",
    "p6:3",
    "p6:4",
    "p6:5",
    "p6:6",
    "p6:7",
    "p6:8",
    "p6:9",
    "p6:10",
    "p8:0",
    "p8:1",
    "p8:2",
    "p8:3",
    "p8:4",
    "p8:5",
    "p8:6",
    "p8:7",
    "p8:8",
    "p8:9",
    "p8:10",
    "p8:11",
    "p8:12",
    "p8:13",
    "p8:14",
    "p8:15",
    "p8:16",
    "p8:17",
    "p8:18",
    "p8:19",
    "p8:20",
    "p8:21",
    "p8:22",
    "p8:23",
    "p8:24",
    "p8:25",
    "p8:26",
    "p8:27",
    "p8:28",
    "p8:29",
    "p8:30",
    "p8:31",
    "p8:32",
    "p8:33",
    "p8:34",
    "p8:35",
    "p8:36",
    "p8:37",
    "p8:38",
    "p8:39",
    "p8:40",
    "p8:41",
    "p8:42",
    "p8:43",
    "p9:0",
    "p9:1",
    "p9:2",
    "p9:3",
    "p9:4",
    "p9:5",
    "p9:6",
    "p9:7",
    "p9:8",
    "p9:9",
    "p9:10",
    "p9:11",
    "p9:12",
    "p9:13",
    "p9:14",
    "p9:15",
    "p9:16",
    "p9:17",
    "p9:18",
    "p9:19",
    "p9:20",
    "p9:21",
    "p9:22",
    "p9:23",
    "p9:24",
    "p9:25",
    "p9:26",
    "p9:27",
    "p9:28",
    "p9:29",
    "p9:30"
  ],
  "findings": [
    {
      "category": "reference_span_error",
      "severity": "critical",
      "block_ids": [
        "p8:15"
      ],
      "truth": "block should remain outside the accepted reference span",
      "pipeline_behavior": "block appears inside the logical reference reading-order region",
      "root_cause_hypothesis": "logical_order_between_reference_members",
      "evidence": {
        "annotated_page": "annotated_pages/page_008.png",
        "artifact": "reference_span_audit.json"
      }
    },
    {
      "category": "reference_span_error",
      "severity": "critical",
      "block_ids": [
        "p8:16"
      ],
      "truth": "block should remain outside the accepted reference span",
      "pipeline_behavior": "block appears inside the logical reference reading-order region",
      "root_cause_hypothesis": "logical_order_between_reference_members",
      "evidence": {
        "annotated_page": "annotated_pages/page_008.png",
        "artifact": "reference_span_audit.json"
      }
    },
    {
      "category": "reference_span_error",
      "severity": "critical",
      "block_ids": [
        "p8:17"
      ],
      "truth": "block should remain outside the accepted reference span",
      "pipeline_behavior": "block appears inside the logical reference reading-order region",
      "root_cause_hypothesis": "logical_order_between_reference_members",
      "evidence": {
        "annotated_page": "annotated_pages/page_008.png",
        "artifact": "reference_span_audit.json"
      }
    },
    {
      "category": "reference_span_error",
      "severity": "critical",
      "block_ids": [
        "p8:18"
      ],
      "truth": "block should remain outside the accepted reference span",
      "pipeline_behavior": "block appears inside the logical reference reading-order region",
      "root_cause_hypothesis": "logical_order_between_reference_members",
      "evidence": {
        "annotated_page": "annotated_pages/page_008.png",
        "artifact": "reference_span_audit.json"
      }
    },
    {
      "category": "reference_span_error",
      "severity": "critical",
      "block_ids": [
        "p8:19"
      ],
      "truth": "block should remain outside the accepted reference span",
      "pipeline_behavior": "block appears inside the logical reference reading-order region",
      "root_cause_hypothesis": "logical_order_between_reference_members",
      "evidence": {
        "annotated_page": "annotated_pages/page_008.png",
        "artifact": "reference_span_audit.json"
      }
    },
    {
      "category": "reference_span_error",
      "severity": "critical",
      "block_ids": [
        "p8:20"
      ],
      "truth": "block should remain outside the accepted reference span",
      "pipeline_behavior": "block appears inside the logical reference reading-order region",
      "root_cause_hypothesis": "logical_order_between_reference_members",
      "evidence": {
        "annotated_page": "annotated_pages/page_008.png",
        "artifact": "reference_span_audit.json"
      }
    },
    {
      "category": "reference_span_error",
      "severity": "critical",
      "block_ids": [
        "p8:21"
      ],
      "truth": "block should remain outside the accepted reference span",
      "pipeline_behavior": "block appears inside the logical reference reading-order region",
      "root_cause_hypothesis": "logical_order_between_reference_members",
      "evidence": {
        "annotated_page": "annotated_pages/page_008.png",
        "artifact": "reference_span_audit.json"
      }
    },
    {
      "category": "reference_span_error",
      "severity": "critical",
      "block_ids": [
        "p8:22"
      ],
      "truth": "block should remain outside the accepted reference span",
      "pipeline_behavior": "block appears inside the logical reference reading-order region",
      "root_cause_hypothesis": "logical_order_between_reference_members",
      "evidence": {
        "annotated_page": "annotated_pages/page_008.png",
        "artifact": "reference_span_audit.json"
      }
    },
    {
      "category": "reference_span_error",
      "severity": "critical",
      "block_ids": [
        "p8:23"
      ],
      "truth": "block should remain outside the accepted reference span",
      "pipeline_behavior": "block appears inside the logical reference reading-order region",
      "root_cause_hypothesis": "logical_order_between_reference_members",
      "evidence": {
        "annotated_page": "annotated_pages/page_008.png",
        "artifact": "reference_span_audit.json"
      }
    },
    {
      "category": "reference_span_error",
      "severity": "critical",
      "block_ids": [
        "p8:24"
      ],
      "truth": "block should remain outside the accepted reference span",
      "pipeline_behavior": "block appears inside the logical reference reading-order region",
      "root_cause_hypothesis": "logical_order_between_reference_members",
      "evidence": {
        "annotated_page": "annotated_pages/page_008.png",
        "artifact": "reference_span_audit.json"
      }
    },
    {
      "category": "reference_span_error",
      "severity": "critical",
      "block_ids": [
        "p8:25"
      ],
      "truth": "block should remain outside the accepted reference span",
      "pipeline_behavior": "block appears inside the logical reference reading-order region",
      "root_cause_hypothesis": "logical_order_between_reference_members",
      "evidence": {
        "annotated_page": "annotated_pages/page_008.png",
        "artifact": "reference_span_audit.json"
      }
    },
    {
      "category": "reference_span_error",
      "severity": "critical",
      "block_ids": [
        "p8:26"
      ],
      "truth": "block should remain outside the accepted reference span",
      "pipeline_behavior": "block appears inside the logical reference reading-order region",
      "root_cause_hypothesis": "logical_order_between_reference_members",
      "evidence": {
        "annotated_page": "annotated_pages/page_008.png",
        "artifact": "reference_span_audit.json"
      }
    },
    {
      "category": "reference_span_error",
      "severity": "critical",
      "block_ids": [
        "p8:27"
      ],
      "truth": "block should remain outside the accepted reference span",
      "pipeline_behavior": "block appears inside the logical reference reading-order region",
      "root_cause_hypothesis": "logical_order_between_reference_members",
      "evidence": {
        "annotated_page": "annotated_pages/page_008.png",
        "artifact": "reference_span_audit.json"
      }
    },
    {
      "category": "reference_span_error",
      "severity": "critical",
      "block_ids": [
        "p8:28"
      ],
      "truth": "block should remain outside the accepted reference span",
      "pipeline_behavior": "block appears inside the logical reference reading-order region",
      "root_cause_hypothesis": "logical_order_between_reference_members",
      "evidence": {
        "annotated_page": "annotated_pages/page_008.png",
        "artifact": "reference_span_audit.json"
      }
    },
    {
      "category": "reference_span_error",
      "severity": "critical",
      "block_ids": [
        "p8:29"
      ],
      "truth": "block should remain outside the accepted reference span",
      "pipeline_behavior": "block appears inside the logical reference reading-order region",
      "root_cause_hypothesis": "logical_order_between_reference_members",
      "evidence": {
        "annotated_page": "annotated_pages/page_008.png",
        "artifact": "reference_span_audit.json"
      }
    },
    {
      "category": "reference_span_error",
      "severity": "critical",
      "block_ids": [
        "p8:30"
      ],
      "truth": "block should remain outside the accepted reference span",
      "pipeline_behavior": "block appears inside the logical reference reading-order region",
      "root_cause_hypothesis": "logical_order_between_reference_members",
      "evidence": {
        "annotated_page": "annotated_pages/page_008.png",
        "artifact": "reference_span_audit.json"
      }
    },
    {
      "category": "reference_span_error",
      "severity": "critical",
      "block_ids": [
        "p9:0"
      ],
      "truth": "block should remain outside the accepted reference span",
      "pipeline_behavior": "block appears inside the logical reference reading-order region",
      "root_cause_hypothesis": "logical_order_between_reference_members",
      "evidence": {
        "annotated_page": "annotated_pages/page_009.png",
        "artifact": "reference_span_audit.json"
      }
    },
    {
      "category": "reference_span_error",
      "severity": "critical",
      "block_ids": [
        "p9:1"
      ],
      "truth": "block should remain outside the accepted reference span",
      "pipeline_behavior": "block appears inside the logical reference reading-order region",
      "root_cause_hypothesis": "logical_order_between_reference_members",
      "evidence": {
        "annotated_page": "annotated_pages/page_009.png",
        "artifact": "reference_span_audit.json"
      }
    },
    {
      "category": "reference_span_error",
      "severity": "critical",
      "block_ids": [
        "p9:2"
      ],
      "truth": "block should remain outside the accepted reference span",
      "pipeline_behavior": "block appears inside the logical reference reading-order region",
      "root_cause_hypothesis": "logical_order_between_reference_members",
      "evidence": {
        "annotated_page": "annotated_pages/page_009.png",
        "artifact": "reference_span_audit.json"
      }
    },
    {
      "category": "reference_span_error",
      "severity": "critical",
      "block_ids": [
        "p9:3"
      ],
      "truth": "block should remain outside the accepted reference span",
      "pipeline_behavior": "block appears inside the logical reference reading-order region",
      "root_cause_hypothesis": "logical_order_between_reference_members",
      "evidence": {
        "annotated_page": "annotated_pages/page_009.png",
        "artifact": "reference_span_audit.json"
      }
    },
    {
      "category": "frontmatter_error",
      "severity": "major",
      "block_ids": [],
      "truth": "page 1 should have clearer frontmatter role resolution",
      "pipeline_behavior": "frontmatter page retains elevated unknown_structural density",
      "root_cause_hypothesis": "frontmatter anchor or noise routing weakness",
      "evidence": {
        "annotated_page": "annotated_pages/page_001.png",
        "artifact": "page_risk_summary.json"
      }
    },
    {
      "category": "same_page_boundary_error",
      "severity": "major",
      "block_ids": [],
      "truth": "body/reference/backmatter boundaries should be explainable at block level",
      "pipeline_behavior": "page contains mixed body/reference/tail signals",
      "root_cause_hypothesis": "same-page boundary ambiguity",
      "evidence": {
        "annotated_page": "annotated_pages/page_008.png",
        "artifact": "page_risk_summary.json"
      }
    },
    {
      "category": "same_page_boundary_error",
      "severity": "major",
      "block_ids": [],
      "truth": "body/reference/backmatter boundaries should be explainable at block level",
      "pipeline_behavior": "page contains mixed body/reference/tail signals",
      "root_cause_hypothesis": "same-page boundary ambiguity",
      "evidence": {
        "annotated_page": "annotated_pages/page_009.png",
        "artifact": "page_risk_summary.json"
      }
    },
    {
      "category": "render_mapping_error",
      "severity": "minor",
      "block_ids": [
        "p1:0",
        "p1:2",
        "p1:5",
        "p1:21",
        "p2:0",
        "p2:1",
        "p2:2",
        "p2:3",
        "p3:0",
        "p3:1",
        "p3:2",
        "p4:0",
        "p4:1",
        "p4:2",
        "p5:0",
        "p5:1",
        "p6:0",
        "p6:1",
        "p6:2",
        "p6:3"
      ],
      "truth": "rendered fulltext should be traceable back to source blocks",
      "pipeline_behavior": "some render-default blocks are not easily mapped into the current fulltext output",
      "root_cause_hypothesis": "render omission or snippet mismatch",
      "evidence": {
        "annotated_page": null,
        "artifact": "fulltext_block_mapping_summary.json"
      }
    }
  ]
}